pyqt5_plugins-5.15.4.2.1.data/purelib/pyqt5_plugins/__init__.py
pyqt5_plugins-5.15.4.2.1.data/purelib/pyqt5_plugins/_version.py
pyqt5_plugins-5.15.4.2.1.data/purelib/pyqt5_plugins/examplebutton.py
pyqt5_plugins-5.15.4.2.1.data/purelib/pyqt5_plugins/examplebuttonplugin.py
pyqt5_plugins-5.15.4.2.1.data/purelib/pyqt5_plugins/utilities.py
pyqt5_plugins-5.15.4.2.1.data/purelib/pyqt5_plugins/Qt/plugins/libpyqt5qmlplugin.dylib
pyqt5_plugins-5.15.4.2.1.data/purelib/pyqt5_plugins/Qt/plugins/designer/libpyqt5.dylib
pyqt5_plugins-5.15.4.2.1.data/purelib/pyqt5_plugins/badplugin/__init__.py
pyqt5_plugins-5.15.4.2.1.data/purelib/pyqt5_plugins/badplugin/badwidgetplugin.py
pyqt5_plugins-5.15.4.2.1.data/purelib/pyqt5_plugins/examples/__init__.py
pyqt5_plugins-5.15.4.2.1.data/purelib/pyqt5_plugins/examples/exampleqmlitem.py
pyqt5_plugins-5.15.4.2.1.data/purelib/pyqt5_plugins/examples/exampleqmlitemplugin.py
pyqt5_plugins-5.15.4.2.1.data/purelib/pyqt5_plugins/examples/libpyqt5qmlplugin.dylib
pyqt5_plugins-5.15.4.2.1.data/purelib/pyqt5_plugins/examples/qmlapp.qml
pyqt5_plugins-5.15.4.2.1.data/purelib/pyqt5_plugins/examples/qmldir
pyqt5_plugins-5.15.4.2.1.data/purelib/pyqt5_plugins/examples/qmltest.qml
pyqt5_plugins-5.15.4.2.1.data/purelib/pyqt5_plugins/tests/__init__.py
pyqt5_plugins-5.15.4.2.1.data/purelib/pyqt5_plugins/tests/test_plugins.py
pyqt5_plugins-5.15.4.2.1.data/purelib/pyqt5_plugins/tests/testbutton.py
pyqt5_plugins-5.15.4.2.1.data/purelib/pyqt5_plugins/tests/testbuttonplugin.py
pyqt5_plugins-5.15.4.2.1.dist-info/COPYING
pyqt5_plugins-5.15.4.2.1.dist-info/METADATA
pyqt5_plugins-5.15.4.2.1.dist-info/WHEEL
pyqt5_plugins-5.15.4.2.1.dist-info/top_level.txt
pyqt5_plugins-5.15.4.2.1.dist-info/RECORD
