Metadata-Version: 2.1
Name: pyqt5-plugins
Version: 5.15.4.2.1
Summary: PyQt Designer and QML plugins
Home-page: https://github.com/altendky/pyqt5-tools
Author: Kyle Altendorf
Author-email: sda@fstab.net
License: GPLv3
Platform: UNKNOWN
Classifier: Development Status :: 4 - Beta
Classifier: Intended Audience :: Developers
Classifier: License :: OSI Approved :: GNU General Public License v3 (GPLv3)
Classifier: Operating System :: POSIX :: Linux
Classifier: Operating System :: MacOS :: MacOS X
Classifier: Operating System :: Microsoft :: Windows
Classifier: Programming Language :: Python :: 3
Classifier: Programming Language :: Python :: 3.5
Classifier: Programming Language :: Python :: 3.6
Classifier: Programming Language :: Python :: 3.7
Classifier: Programming Language :: Python :: 3.8
Classifier: Programming Language :: Python :: 3.9
Classifier: Topic :: Software Development
Classifier: Topic :: Utilities
Requires-Python: >=3.5
Requires-Dist: click
Requires-Dist: pyqt5 (==5.15.4)
Requires-Dist: qt5-tools (<5.15.2.2,>=5.15.2.1.1)
